{
    "name": "Peugeot 406",
    "type": "road",
    "id": "406sd",
    "version": "Sedan",
    "year": 1999,
    "engine": {
      "displacement": "2.0",
      "type": "I4",
      "power": 139,
      "torque": 18.4
    },
    "dimensions": {
      "length": 4555,
      "width": 1765,
      "height": 1396,
      "weight": 1390
    },
    "price": "44.390",
    "drivetrain": "ff",
    "defaultColour": 0,
    "colours": [
      { "name": "Platinum Gray", "hex": "#888c8c" },
      { "name": "Vulcan Red", "hex": "#201110" },
      { "name": "Sherwood Green", "hex": "#102011" },
      { "name": "China Blue", "hex": "#181828" }
    ]
  }
  